xradar/__init__.py
xradar/accessors.py
xradar/model.py
xradar/util.py
xradar/version.py
xradar/xradar.py
xradar/georeference/__init__.py
xradar/georeference/projection.py
xradar/georeference/transforms.py
xradar/io/__init__.py
xradar/io/backends/__init__.py
xradar/io/backends/cfradial1.py
xradar/io/backends/common.py
xradar/io/backends/datamet.py
xradar/io/backends/furuno.py
xradar/io/backends/gamic.py
xradar/io/backends/hpl.py
xradar/io/backends/iris.py
xradar/io/backends/metek.py
xradar/io/backends/nexrad_level2.py
xradar/io/backends/odim.py
xradar/io/backends/rainbow.py
xradar/io/export/__init__.py
xradar/io/export/cfradial1.py
xradar/io/export/cfradial2.py
xradar/io/export/odim.py
xradar/transform/__init__.py
xradar/transform/cfradial.py
xradar-0.8.0.dist-info/AUTHORS.md
xradar-0.8.0.dist-info/LICENSE
xradar-0.8.0.dist-info/METADATA
xradar-0.8.0.dist-info/WHEEL
xradar-0.8.0.dist-info/entry_points.txt
xradar-0.8.0.dist-info/top_level.txt
xradar-0.8.0.dist-info/RECORD
