Metadata-Version: 2.1
Name: xradar
Version: 0.8.0
Summary: Xradar includes all the tools to get your weather radar into the xarray data model.
Author-email: Maxwell Grover <mgrover@anl.gov>, Kai Mühlbauer <kai.muehlbauer@uni-bonn.de>, Zachary Sherman <zsherman@anl.gov>
License: MIT License
Project-URL: homepage, https://docs.openradarscience.org/projects/xradar
Project-URL: documentation, https://docs.openradarscience.org/projects/xradar/
Project-URL: repository, https://github.com/openradar/xradar
Project-URL: changelog, https://github.com/openradar/xradar/blob/main/docs/history.md
Keywords: xradar
Classifier: Development Status :: 4 - Beta
Classifier: Intended Audience :: Developers
Classifier: Intended Audience :: Education
Classifier: Intended Audience :: Science/Research
Classifier: License :: OSI Approved :: MIT License
Classifier: Natural Language :: English
Classifier: Operating System :: OS Independent
Classifier: Programming Language :: Python :: 3
Classifier: Programming Language :: Python :: 3.9
Classifier: Programming Language :: Python :: 3.10
Classifier: Programming Language :: Python :: 3.11
Classifier: Programming Language :: Python :: 3.12
Classifier: Topic :: Scientific/Engineering
Classifier: Topic :: Scientific/Engineering :: Atmospheric Science
Requires-Python: >=3.9
License-File: LICENSE
License-File: AUTHORS.md
Requires-Dist: cmweather
Requires-Dist: dask
Requires-Dist: h5netcdf>=1.0.0
Requires-Dist: h5py>=3.0.0
Requires-Dist: lat-lon-parser
Requires-Dist: netCDF4
Requires-Dist: numpy
Requires-Dist: pyproj
Requires-Dist: scipy
Requires-Dist: xarray>=2024.10.0
Requires-Dist: xmltodict
Provides-Extra: dev
Requires-Dist: pip; extra == "dev"
Requires-Dist: wheel; extra == "dev"
Requires-Dist: watchdog; extra == "dev"
Requires-Dist: flake8; extra == "dev"
Requires-Dist: tox; extra == "dev"
Requires-Dist: coverage; extra == "dev"
Requires-Dist: Sphinx; extra == "dev"
Requires-Dist: twine; extra == "dev"
Requires-Dist: pytest; extra == "dev"
Requires-Dist: black; extra == "dev"
Requires-Dist: isort; extra == "dev"
Requires-Dist: fsspec; extra == "dev"
